{"name":"javaScript高级程序设计笔记","permalink":"http://blog.hellolc.com/tags/javaScript高级程序设计笔记/","url":"/async/tags/javaScript高级程序设计笔记.json","count":17,"_total":17,"_totalPage":2,"_page":2,"posts":[{"tags":[{"name":"javaScript高级程序设计笔记","permalink":"http://blog.hellolc.com/tags/javaScript高级程序设计笔记/","url":"/async/tags/javaScript高级程序设计笔记.json","count":17}],"categories":[],"url":"/async/posts/2017/07/06/函数表达式.json","date":1499304371000,"path":{"year":2017,"month":7,"day":6,"name":"函数表达式"},"title":"函数表达式","permalink":"http://blog.hellolc.com/2017/07/06/函数表达式/","content":""},{"tags":[{"name":"javaScript高级程序设计笔记","permalink":"http://blog.hellolc.com/tags/javaScript高级程序设计笔记/","url":"/async/tags/javaScript高级程序设计笔记.json","count":17}],"categories":[],"url":"/async/posts/2017/07/13/客户端检测.json","date":1499909394000,"path":{"year":2017,"month":7,"day":13,"name":"客户端检测"},"title":"客户端检测","permalink":"http://blog.hellolc.com/2017/07/13/客户端检测/","content":""},{"tags":[{"name":"javaScript高级程序设计笔记","permalink":"http://blog.hellolc.com/tags/javaScript高级程序设计笔记/","url":"/async/tags/javaScript高级程序设计笔记.json","count":17}],"categories":[],"url":"/async/posts/2017/09/23/最佳实践.json","date":1506166315000,"path":{"year":2017,"month":9,"day":23,"name":"最佳实践"},"title":"最佳实践","permalink":"http://blog.hellolc.com/2017/09/23/最佳实践/","content":""},{"tags":[{"name":"javaScript高级程序设计笔记","permalink":"http://blog.hellolc.com/tags/javaScript高级程序设计笔记/","url":"/async/tags/javaScript高级程序设计笔记.json","count":17}],"categories":[],"url":"/async/posts/2017/06/29/引用类型.json","date":1498700026000,"path":{"year":2017,"month":6,"day":29,"name":"引用类型"},"title":"引用类型","permalink":"http://blog.hellolc.com/2017/06/29/引用类型/","content":""},{"tags":[{"name":"javaScript高级程序设计笔记","permalink":"http://blog.hellolc.com/tags/javaScript高级程序设计笔记/","url":"/async/tags/javaScript高级程序设计笔记.json","count":17}],"categories":[],"url":"/async/posts/2017/09/18/离线应用与客户端存储.json","date":1505699666000,"path":{"year":2017,"month":9,"day":18,"name":"离线应用与客户端存储"},"title":"离线应用与客户端存储","permalink":"http://blog.hellolc.com/2017/09/18/离线应用与客户端存储/","content":""},{"tags":[{"name":"javaScript高级程序设计笔记","permalink":"http://blog.hellolc.com/tags/javaScript高级程序设计笔记/","url":"/async/tags/javaScript高级程序设计笔记.json","count":17}],"categories":[],"url":"/async/posts/2017/06/29/面向对象的程序设计.json","date":1498703108000,"path":{"year":2017,"month":6,"day":29,"name":"面向对象的程序设计"},"title":"面向对象的程序设计","permalink":"http://blog.hellolc.com/2017/06/29/面向对象的程序设计/","content":""},{"tags":[{"name":"javaScript高级程序设计笔记","permalink":"http://blog.hellolc.com/tags/javaScript高级程序设计笔记/","url":"/async/tags/javaScript高级程序设计笔记.json","count":17}],"categories":[],"url":"/async/posts/2017/09/12/高级技巧.json","date":1505184037000,"path":{"year":2017,"month":9,"day":12,"name":"高级技巧"},"title":"高级技巧","permalink":"http://blog.hellolc.com/2017/09/12/高级技巧/","content":""}]}